__init__.py
api_client.py
api_response.py
configuration.py
exceptions.py
py.typed
rest.py
openapi_client_gladkii-1.0.2.dist-info/LICENSE
openapi_client_gladkii-1.0.2.dist-info/METADATA
openapi_client_gladkii-1.0.2.dist-info/WHEEL
openapi_client_gladkii-1.0.2.dist-info/RECORD
